icetrust/__init__.py
icetrust/cli.py
icetrust/utils.py
icetrust/utils_canary.py
icetrust/data/canary_input.schema.json
icetrust/data/canary_output.schema.json
icetrust-0.1.6.dist-info/LICENSE
icetrust-0.1.6.dist-info/METADATA
icetrust-0.1.6.dist-info/WHEEL
icetrust-0.1.6.dist-info/entry_points.txt
icetrust-0.1.6.dist-info/top_level.txt
icetrust-0.1.6.dist-info/RECORD
