Metadata-Version: 2.1
Name: icetrust
Version: 0.1.6
Summary: A tool for verification of software downloads using checksums and PGP.
Home-page: https://github.com/nightwatchcybersecurity/icetrust
Author: Nightwatch Cybersecurity
Author-email: research@nightwatchcybersecurity.com
License: Apache
Project-URL: Bug Reports, https://github.com/nightwatchcybersecurity/icetrust/issues
Project-URL: Source, https://github.com/nightwatchcybersecurity/icetrust
Platform: UNKNOWN
Classifier: Environment :: Console
Classifier: Development Status :: 3 - Alpha
Classifier: License :: OSI Approved :: Apache Software License
Classifier: Operating System :: OS Independent
Classifier: Programming Language :: Python :: 3.6
Classifier: Programming Language :: Python :: 3.7
Classifier: Programming Language :: Python :: 3.8
Classifier: Programming Language :: Python :: 3.9
Requires-Python: >=3.6
Requires-Dist: click (>=7.1.2)
Requires-Dist: download (>=0.3.5)
Requires-Dist: filehash (>=0.1.dev5)
Requires-Dist: jsonschema (>=3.2.0)
Requires-Dist: requests (>=2.23)
Requires-Dist: python-gnupg (>=0.4.7)
Requires-Dist: tzlocal (>=2.1)
Requires-Dist: pytest (>=6.2.0)
Requires-Dist: pytest-cov (>=2.11.1)
Requires-Dist: pytest-optional-tests (>=0.1.1)
